{
	"name": "AzureDataLakeStorage_teste",
	"properties": {
		"annotations": [],
		"type": "AzureBlobFS",
		"typeProperties": {
			"url": "https://storagesabrina2.dfs.core.windows.net/",
			"accountKey": {
				"type": "AzureKeyVaultSecret",
				"store": {
					"referenceName": "AzureKeyVault_testesabrina",
					"type": "LinkedServiceReference"
				},
				"secretName": "storagekey",
				"secretVersion": "38e37e02768848d1b1cd777a92f50184"
			}
		}
	},
	"type": "Microsoft.DataFactory/factories/linkedservices"
}